{
  "ids": {
    "Session": 13
  },
  "models": {
    "Session": {
      "shuki": "{\"sid\":\"shuki\",\"statusCode\":2,\"pkgs\":[{\"name\":\"shuki@12\",\"statusCode\":4,\"msg\":\"success\"},{\"name\":\"shukitest@12\",\"statusCode\":2,\"msg\":\"failed\"}]}",
      "shuki10": "{\"sid\":\"shuki10\",\"statusCode\":2,\"pkgs\":[{\"name\":\"shuki@12\",\"statusCode\":4,\"msg\":\"success\"},{\"name\":\"shukitest@12\",\"statusCode\":2,\"msg\":\"failed\"}]}",
      "shuki10qw": "{\"sid\":\"shuki10qw\",\"statusCode\":2,\"pkgs\":[{\"name\":\"shuki@12\",\"statusCode\":4,\"msg\":\"success\"},{\"name\":\"shukitest@12\",\"statusCode\":2,\"msg\":\"failed\"}]}",
      "shuki10asdqw": "{\"sid\":\"shuki10asdqw\",\"statusCode\":2,\"pkgs\":[{\"name\":\"shuki@12\",\"statusCode\":4,\"msg\":\"success\"},{\"name\":\"shukitest@12\",\"statusCode\":2,\"msg\":\"failed\"}]}",
      "shuki10asasddqw": "{\"sid\":\"shuki10asasddqw\",\"statusCode\":2,\"pkgs\":[{\"name\":\"shuki@12\",\"statusCode\":4,\"msg\":\"success\"},{\"name\":\"shukitest@12\",\"statusCode\":2,\"msg\":\"failed\"}]}",
      "shuki10asasasdddqw": "{\"sid\":\"shuki10asasasdddqw\",\"statusCode\":2,\"pkgs\":[{\"name\":\"shuki@12\",\"statusCode\":4,\"msg\":\"success\"},{\"name\":\"shukitest@12\",\"statusCode\":2,\"msg\":\"failed\"}]}",
      "shuasdki10asasasdddqw": "{\"sid\":\"shuasdki10asasasdddqw\",\"statusCode\":2,\"pkgs\":[{\"name\":\"shuki@12\",\"statusCode\":4,\"msg\":\"success\"},{\"name\":\"shukitest@12\",\"statusCode\":2,\"msg\":\"failed\"}]}",
      "shuaaasdki10asasasdddqw": "{\"sid\":\"shuaaasdki10asasasdddqw\",\"statusCode\":2,\"pkgs\":[{\"name\":\"shuki@12\",\"statusCode\":4,\"msg\":\"success\"},{\"name\":\"shukitest@12\",\"statusCode\":2,\"msg\":\"failed\"}]}",
      "shuaaasdki10asaasdsasdddqw": "{\"sid\":\"shuaaasdki10asaasdsasdddqw\",\"statusCode\":2,\"pkgs\":[{\"name\":\"shuki@12\",\"statusCode\":4,\"msg\":\"success\"},{\"name\":\"shukitest@12\",\"statusCode\":2,\"msg\":\"failed\"}]}",
      "shuaaasdkwi10asaasdsasdddqw": "{\"sid\":\"shuaaasdkwi10asaasdsasdddqw\",\"statusCode\":2,\"pkgs\":[{\"name\":\"shuki@12\",\"statusCode\":4,\"msg\":\"success\"},{\"name\":\"shukitest@12\",\"statusCode\":2,\"msg\":\"failed\"}]}",
      "shuaaasdkwi1asd0asaasdsasdddqw": "{\"sid\":\"shuaaasdkwi1asd0asaasdsasdddqw\",\"statusCode\":2,\"pkgs\":[{\"name\":\"shuki@12\",\"statusCode\":4,\"msg\":\"success\"},{\"name\":\"shukitest@12\",\"statusCode\":2,\"msg\":\"failed\"}]}"
    }
  }
}